PyVALION/__init__.py
PyVALION/library.py
PyVALION/plotting.py
PyVALION/giro_names/GIRO_Ionosondes.p
pyvalion-0.0.1.dist-info/licenses/LICENSE
pyvalion-0.0.1.dist-info/METADATA
pyvalion-0.0.1.dist-info/WHEEL
pyvalion-0.0.1.dist-info/top_level.txt
pyvalion-0.0.1.dist-info/RECORD
